statcore/__init__.py
statcore/algos.py
statcore/array.py
statcore/linear.py
statcore/main.py
statcore/matrix.py
statcore/objs.py
statcore/tensor.py
tests/__init__.py
tests/test_algos.py
tests/test_linear.py
statcore-0.0.2.dist-info/METADATA
statcore-0.0.2.dist-info/WHEEL
statcore-0.0.2.dist-info/top_level.txt
statcore-0.0.2.dist-info/RECORD
