Metadata-Version: 2.1
Name: statcore
Version: 0.0.2
Summary: UNKNOWN
Author: Andrew Barisser
License: MIT
Platform: UNKNOWN
Requires-Dist: numpy
